pygerduty/__init__.py
pygerduty/common.py
pygerduty/events.py
pygerduty/v2.py
pygerduty/version.py
pygerduty-0.38.1.data/scripts/grab_oncall.py
pygerduty-0.38.1.dist-info/DESCRIPTION.rst
pygerduty-0.38.1.dist-info/METADATA
pygerduty-0.38.1.dist-info/RECORD
pygerduty-0.38.1.dist-info/WHEEL
pygerduty-0.38.1.dist-info/metadata.json
pygerduty-0.38.1.dist-info/top_level.txt
