Metadata-Version: 2.0
Name: pygerduty
Version: 0.38.1
Summary: Python Client Library for PagerDuty's REST API
Home-page: https://github.com/dropbox/pygerduty
Author: Mike Cugini
Author-email: cugini@dropbox.com
Maintainer: Mike Cugini
Maintainer-email: cugini@dropbox.com
License: MIT
Download-URL: https://github.com/dropbox/pygerduty/archive/master.tar.gz
Platform: UNKNOWN
Classifier: Programming Language :: Python
Classifier: Topic :: Software Development
Classifier: Topic :: Software Development :: Libraries
Classifier: Topic :: Software Development :: Libraries :: Python Modules
Requires-Dist: six
